pvkoalademo/LICENSE
pvkoalademo/koala_demo_file.py
pvkoalademo/koala_demo_mic.py
pvkoalademo-3.0.0.dist-info/METADATA
pvkoalademo-3.0.0.dist-info/WHEEL
pvkoalademo-3.0.0.dist-info/entry_points.txt
pvkoalademo-3.0.0.dist-info/top_level.txt
pvkoalademo-3.0.0.dist-info/RECORD
